{"version":1,"resource":"file:///home/pranav/code/D_Mathematical_Problem.cpp","entries":[{"id":"X01E.cpp","timestamp":1719156046613},{"id":"6Qqh.cpp","timestamp":1719156165793},{"id":"vNuG.cpp","timestamp":1719156230367},{"id":"8OZ2.cpp","timestamp":1719156269709},{"id":"t36V.cpp","timestamp":1719156317843},{"id":"Elxc.cpp","timestamp":1719156362342},{"id":"GDw6.cpp","timestamp":1719156533996},{"id":"XARD.cpp","timestamp":1719156704675},{"id":"l0ZK.cpp","timestamp":1719156800760},{"id":"2RWW.cpp","timestamp":1719156834050},{"id":"oQGT.cpp","timestamp":1719156884163},{"id":"2EML.cpp","timestamp":1719156914989},{"id":"ugqv.cpp","timestamp":1719156938755},{"id":"AhbT.cpp","timestamp":1719160815313}]}