{"version":1,"resource":"file:///home/pranav/code/C_Squaring.cpp","entries":[{"id":"vb9D.cpp","timestamp":1722085025400},{"id":"9zUS.cpp","timestamp":1722173890570},{"id":"uh9k.cpp","timestamp":1722173911000},{"id":"9PxO.cpp","timestamp":1722173987464},{"id":"TIyj.cpp","timestamp":1722174030741},{"id":"luqZ.cpp","timestamp":1722174085714},{"id":"KNVZ.cpp","timestamp":1722174210811},{"id":"mSXg.cpp","timestamp":1722174286990},{"id":"gYro.cpp","timestamp":1722174310068},{"id":"tfZj.cpp","timestamp":1722174351465},{"id":"UIxJ.cpp","timestamp":1722174465232},{"id":"v1rI.cpp","timestamp":1722174523567},{"id":"KCUg.cpp","timestamp":1722284353016},{"id":"obkp.cpp","timestamp":1722284435228},{"id":"rBQ0.cpp","timestamp":1722284474894},{"id":"DbcI.cpp","timestamp":1722284538249},{"id":"86Tv.cpp","timestamp":1722284700864},{"id":"gG7D.cpp","timestamp":1722284756430},{"id":"odmE.cpp","timestamp":1722284773110},{"id":"xL0E.cpp","timestamp":1722284813489},{"id":"CFYq.cpp","timestamp":1722284904489},{"id":"qiau.cpp","timestamp":1722284925686},{"id":"q4Nl.cpp","timestamp":1722285172666},{"id":"ashz.cpp","timestamp":1722285221551},{"id":"gJrX.cpp","timestamp":1722285233713}]}