{"version":1,"resource":"file:///home/pranav/code/C_Bakry_and_Partitioning.cpp","entries":[{"id":"N3FJ.cpp","timestamp":1720557041462},{"id":"ljkR.cpp","timestamp":1720557064470},{"id":"ifRK.cpp","timestamp":1720557085746},{"id":"fDya.cpp","timestamp":1720557134426},{"id":"KCUW.cpp","timestamp":1720557153221},{"id":"3fql.cpp","timestamp":1720557175618},{"id":"wrzf.cpp","timestamp":1720557205478},{"id":"pRRZ.cpp","timestamp":1720557279040},{"id":"HOAv.cpp","timestamp":1720557593123},{"id":"ObXo.cpp","timestamp":1720557700160},{"id":"mewf.cpp","timestamp":1720557774114},{"id":"SHAt.cpp","timestamp":1720557784191},{"id":"LQGH.cpp","timestamp":1720557809421},{"id":"rkPx.cpp","timestamp":1720557882838},{"id":"mCSY.cpp","timestamp":1720557939209},{"id":"eelT.cpp","timestamp":1720558085770},{"id":"yVWW.cpp","timestamp":1720608268162},{"id":"IAvc.cpp","timestamp":1720608667226},{"id":"9MBE.cpp","timestamp":1720608742979},{"id":"pJz8.cpp","timestamp":1720609009356},{"id":"kPXf.cpp","timestamp":1720611007389},{"id":"QiYC.cpp","timestamp":1720611063353},{"id":"a6uP.cpp","timestamp":1720611087939},{"id":"Xo3l.cpp","timestamp":1720611134528},{"id":"kpOQ.cpp","timestamp":1720611194086},{"id":"FINm.cpp","timestamp":1720611286776},{"id":"uiwq.cpp","timestamp":1720611307211},{"id":"Hna2.cpp","timestamp":1720611610744},{"id":"f4X4.cpp","timestamp":1720612361893},{"id":"xNfg.cpp","timestamp":1720612386896},{"id":"mJr2.cpp","timestamp":1720612725493},{"id":"DT3e.cpp","timestamp":1720612840852},{"id":"ti9G.cpp","timestamp":1720613073914},{"id":"jyds.cpp","timestamp":1720613663887},{"id":"Podx.cpp","timestamp":1720613760261},{"id":"Njzb.cpp","timestamp":1720613857885},{"id":"tQE5.cpp","timestamp":1720613895965},{"id":"gg37.cpp","timestamp":1720614108560},{"id":"zyXV.cpp","timestamp":1720614483893},{"id":"FPoI.cpp","timestamp":1720614517585},{"id":"U5QF.cpp","timestamp":1720614915283},{"id":"PQdw.cpp","timestamp":1720618144580},{"id":"wggI.cpp","source":"undoRedo.source","timestamp":1720618301097},{"id":"OujQ.cpp","timestamp":1721057785659}]}